glean/agent_toolkit/__init__.py
glean/agent_toolkit/decorators.py
glean/agent_toolkit/py.typed
glean/agent_toolkit/registry.py
glean/agent_toolkit/spec.py
glean/agent_toolkit/adapters/__init__.py
glean/agent_toolkit/adapters/adk.py
glean/agent_toolkit/adapters/base.py
glean/agent_toolkit/adapters/crewai.py
glean/agent_toolkit/adapters/langchain.py
glean/agent_toolkit/adapters/openai.py
glean/agent_toolkit/tools/__init__.py
glean/agent_toolkit/tools/_common.py
glean/agent_toolkit/tools/ai_web_search.py
glean/agent_toolkit/tools/calendar_search.py
glean/agent_toolkit/tools/code_search.py
glean/agent_toolkit/tools/employee_search.py
glean/agent_toolkit/tools/glean_search.py
glean/agent_toolkit/tools/gmail_search.py
glean/agent_toolkit/tools/outlook_search.py
glean/agent_toolkit/tools/web_search.py
glean_agent_toolkit-0.2.0.dist-info/METADATA
glean_agent_toolkit-0.2.0.dist-info/WHEEL
glean_agent_toolkit-0.2.0.dist-info/licenses/LICENSE
glean_agent_toolkit-0.2.0.dist-info/RECORD
