Metadata-Version: 2.4
Name: glean-agent-toolkit
Version: 0.2.0
Summary: AI Agent toolkit for adapting Glean's enterprise tools across multiple frameworks
Project-URL: Source Code, https://github.com/gleanwork/glean-agent-toolkit
Author-email: Steve Calvert <steve.calvert@glean.com>
License: MIT
License-File: LICENSE
Requires-Python: <4.0,>=3.10
Requires-Dist: glean-api-client<1.0,>=0.6.0
Requires-Dist: pydantic<3.0,>=2.7
Provides-Extra: adk
Requires-Dist: google-adk<1.0,>=0.1.0; extra == 'adk'
Provides-Extra: codespell
Requires-Dist: codespell<3.0,>=2.2.6; extra == 'codespell'
Provides-Extra: crewai
Requires-Dist: crewai<1.0,>=0.28.0; extra == 'crewai'
Provides-Extra: dev
Requires-Dist: commitizen<5.0,>=4.4.1; extra == 'dev'
Requires-Dist: pip-audit<3.0,>=2.6.0; extra == 'dev'
Requires-Dist: vcrpy<7.0,>=6.0.2; extra == 'dev'
Provides-Extra: langchain
Requires-Dist: langchain<1.0,>=0.1.0; extra == 'langchain'
Provides-Extra: lint
Requires-Dist: ruff<1.0,>=0.5; extra == 'lint'
Provides-Extra: openai
Requires-Dist: openai-agents<1.0,>=0.0.11; extra == 'openai'
Requires-Dist: openai<2.0,>=1.0.0; extra == 'openai'
Provides-Extra: test
Requires-Dist: crewai<1.0,>=0.28.0; extra == 'test'
Requires-Dist: google-adk<1.0,>=0.1.0; extra == 'test'
Requires-Dist: langchain<1.0,>=0.1.0; extra == 'test'
Requires-Dist: openai-agents<1.0,>=0.0.11; extra == 'test'
Requires-Dist: openai<2.0,>=1.0.0; extra == 'test'
Requires-Dist: pytest-asyncio<1.0,>=0.23.2; extra == 'test'
Requires-Dist: pytest-cov<6.0,>=4.1.0; extra == 'test'
Requires-Dist: pytest-httpx<1.0,>=0.35.0; extra == 'test'
Requires-Dist: pytest<9.0,>=7.4.3; extra == 'test'
Provides-Extra: typing
Requires-Dist: pyright<2.0,>=1.1.370; extra == 'typing'
